anosys_sdk_openai/__init__.py
anosys_sdk_openai/hooks.py
anosys_sdk_openai/instrumentor.py
anosys_sdk_openai/mapping.py
anosys_sdk_openai/streaming.py
anosys_sdk_openai-1.0.1.dist-info/METADATA
anosys_sdk_openai-1.0.1.dist-info/WHEEL
anosys_sdk_openai-1.0.1.dist-info/top_level.txt
anosys_sdk_openai-1.0.1.dist-info/RECORD
