Metadata-Version: 2.4
Name: anosys-sdk-openai
Version: 1.0.1
Summary: AnoSys SDK for OpenAI - Automatic instrumentation and logging for OpenAI API calls
Author-email: AnoSys <support@anosys.ai>
Project-URL: Homepage, https://anosys.ai
Project-URL: Documentation, https://docs.anosys.ai
Project-URL: Repository, https://github.com/anosys-ai/anosys-sdk
Keywords: anosys,openai,observability,monitoring,logging,llm,gpt
Classifier: Development Status :: 4 - Beta
Classifier: Intended Audience :: Developers
Classifier: License :: OSI Approved :: Apache Software License
Classifier: Programming Language :: Python :: 3
Classifier: Programming Language :: Python :: 3.10
Classifier: Programming Language :: Python :: 3.11
Classifier: Programming Language :: Python :: 3.12
Classifier: Topic :: Software Development :: Libraries :: Python Modules
Classifier: Topic :: System :: Monitoring
Requires-Python: >=3.10
Requires-Dist: anosys-sdk-core>=1.0.0
Requires-Dist: opentelemetry-api>=1.22.0
Requires-Dist: opentelemetry-sdk>=1.22.0
Requires-Dist: traceai-openai>=0.1.0
